elasticsearch_kernel/__init__.py
elasticsearch_kernel/__main__.py
elasticsearch_kernel/install.py
elasticsearch_kernel/kernel.py
elasticsearch_kernel-0.1.0.dist-info/LICENSE.txt
elasticsearch_kernel-0.1.0.dist-info/METADATA
elasticsearch_kernel-0.1.0.dist-info/WHEEL
elasticsearch_kernel-0.1.0.dist-info/top_level.txt
elasticsearch_kernel-0.1.0.dist-info/RECORD
