Metadata-Version: 2.1
Name: elasticsearch-kernel
Version: 0.1.0
Summary: A elasticsearch kernel for Jupyter.
Home-page: https://github.com/Hourout/elasticsearch_kernel
Author: JinQing Lee
Author-email: hourout@163.com
License: Apache License Version 2.0
Keywords: jupyter_kernel,elasticsearch_kernel
Platform: UNKNOWN
Classifier: Framework :: IPython
Classifier: License :: OSI Approved :: Apache Software License
Classifier: Programming Language :: Python :: 3.6
Classifier: Programming Language :: Python :: 3.7
Classifier: Programming Language :: Python :: 3.8
Classifier: Intended Audience :: Developers
Classifier: Intended Audience :: Education
Classifier: Intended Audience :: Science/Research
Classifier: Topic :: Scientific/Engineering
Classifier: Topic :: System :: Shells
Requires-Dist: requests
Requires-Dist: pandas
Requires-Dist: jupyter
